gapps.py
gapps_mod-0.0.8.dist-info/LICENSE
gapps_mod-0.0.8.dist-info/METADATA
gapps_mod-0.0.8.dist-info/WHEEL
gapps_mod-0.0.8.dist-info/top_level.txt
gapps_mod-0.0.8.dist-info/RECORD
