Metadata-Version: 2.2
Name: gapps-mod
Version: 0.0.8
Summary: A wrapper for some Google App functionality (Sheets and email mostly)
Home-page: https://github.com/ejohnfel/gapps
Author: Eric Johnfelt
Author-email: ejohnfel@hotmail.com
Project-URL: Bug Tracker, https://github.com/ejohnfel/gapps/issues
Classifier: Programming Language :: Python :: 3
Classifier: License :: OSI Approved :: MIT License
Classifier: Operating System :: OS Independent
Requires-Python: >=3.0
License-File: LICENSE
Requires-Dist: py-helper-mod
Requires-Dist: google-api-python-client>=2.0.2
Requires-Dist: google-auth-httplib2>=0.1.0
Requires-Dist: google-auth-oauthlib>=0.4.3
